Metadata-Version: 2.2
Name: topsis_102203949
Version: 0.1.0
Summary: A Python implementation of the TOPSIS method for multi-criteria decision analysis
Home-page: https://github.com/aryalal11/topsis
Author: Arya Lal
Author-email: aryalalqms@gmail.com
Classifier: Programming Language :: Python :: 3
Classifier: Operating System :: OS Independent
Requires-Python: >=3.6
Requires-Dist: pandas
Requires-Dist: numpy
Dynamic: author
Dynamic: author-email
Dynamic: classifier
Dynamic: description
Dynamic: description-content-type
Dynamic: home-page
Dynamic: requires-dist
Dynamic: requires-python
Dynamic: summary
